codejail/__init__.py
codejail/django_integration.py
codejail/django_integration_utils.py
codejail/jail_code.py
codejail/proxy.py
codejail/proxy_main.py
codejail/safe_exec.py
codejail/subproc.py
codejail/util.py
edx_codejail-4.1.0.data/scripts/memory_stress.py
edx_codejail-4.1.0.dist-info/licenses/LICENSE.txt
edx_codejail-4.1.0.dist-info/licenses/NOTICE.txt
edx_codejail-4.1.0.dist-info/METADATA
edx_codejail-4.1.0.dist-info/WHEEL
edx_codejail-4.1.0.dist-info/top_level.txt
edx_codejail-4.1.0.dist-info/RECORD
