Metadata-Version: 2.4
Name: edx-codejail
Version: 4.1.0
Summary: CodeJail manages execution of untrusted code in secure sandboxes. It is designed primarily for Python execution, but can be used for other languages as well.
Home-page: https://github.com/openedx/codejail
Author: edX
Author-email: oscm@edx.org
License: Apache
Keywords: edx codejail
Classifier: License :: OSI Approved :: Apache Software License
Classifier: Operating System :: POSIX :: Linux
Classifier: Development Status :: 5 - Production/Stable
Classifier: Intended Audience :: Developers
Classifier: Programming Language :: Python
Classifier: Programming Language :: Python :: 3
Classifier: Programming Language :: Python :: 3.11
Classifier: Programming Language :: Python :: 3.12
License-File: LICENSE.txt
License-File: NOTICE.txt
Requires-Dist: six
Dynamic: author
Dynamic: author-email
Dynamic: classifier
Dynamic: description
Dynamic: home-page
Dynamic: keywords
Dynamic: license
Dynamic: license-file
Dynamic: requires-dist
Dynamic: summary
